FNAPILIB/__init__.py
FNAPILIB-1.0.7.dist-info/LICENCE.txt
FNAPILIB-1.0.7.dist-info/METADATA
FNAPILIB-1.0.7.dist-info/WHEEL
FNAPILIB-1.0.7.dist-info/top_level.txt
FNAPILIB-1.0.7.dist-info/RECORD
