Metadata-Version: 2.1
Name: FNAPILIB
Version: 1.0.7
Summary: Python LIB for FN-api.com
Home-page: UNKNOWN
Author: LKST1
Author-email: leaks.station.guy@gmail.com
License: UNKNOWN
Keywords: FN,fnapi,fortnite,fortnite cosmetics,Fn-api,Fnapi.com,Fortnite status,STW,Fortnite STW
Platform: UNKNOWN
Classifier: Programming Language :: Python :: 3
Classifier: License :: OSI Approved :: MIT License
Classifier: Operating System :: OS Independent
Requires-Python: >=3
License-File: LICENCE.txt
